aerospike_rest/__init__.py
aerospike_rest/api.py
aerospike_rest/exceptions.py
aerospike_rest/tests/__init__.py
aerospike_rest/tests/test_api.py
aerospike_rest-0.2.1.dist-info/LICENSE
aerospike_rest-0.2.1.dist-info/METADATA
aerospike_rest-0.2.1.dist-info/WHEEL
aerospike_rest-0.2.1.dist-info/top_level.txt
aerospike_rest-0.2.1.dist-info/RECORD
