Metadata-Version: 2.1
Name: aerospike-rest
Version: 0.2.1
Summary: Python interface to Aerospike REST Client
Home-page: https://github.com/aerospike-community/aerospike-python-rest
License: UNKNOWN
Platform: UNKNOWN
Classifier: Programming Language :: Python :: 3
Classifier: License :: OSI Approved :: MIT License
Classifier: Operating System :: OS Independent
Requires-Python: >=3.3
License-File: LICENSE
Requires-Dist: requests
